clloader/__init__.py
clloader/loader.py
clloader/viz.py
clloader/datasets/__init__.py
clloader/datasets/base.py
clloader/datasets/fellowship.py
clloader/datasets/imagenet.py
clloader/datasets/pytorch.py
clloader/datasets/transformed.py
tests/__init__.py
tests/test_imagefolder.py
tests/test_inmemory.py
clloader_arthurdouillard-0.0.1.dist-info/LICENSE
clloader_arthurdouillard-0.0.1.dist-info/METADATA
clloader_arthurdouillard-0.0.1.dist-info/WHEEL
clloader_arthurdouillard-0.0.1.dist-info/top_level.txt
clloader_arthurdouillard-0.0.1.dist-info/RECORD
